treejson/__init__.py
treejson/treejson.py
treejson/version.py
treejson-0.1.0.dist-info/DESCRIPTION.rst
treejson-0.1.0.dist-info/METADATA
treejson-0.1.0.dist-info/RECORD
treejson-0.1.0.dist-info/WHEEL
treejson-0.1.0.dist-info/entry_points.txt
treejson-0.1.0.dist-info/metadata.json
treejson-0.1.0.dist-info/pbr.json
treejson-0.1.0.dist-info/top_level.txt
