Metadata-Version: 2.0
Name: treejson
Version: 0.1.0
Summary: This package helps you discover the structure of a JSON string.
Home-page: https://github.com/rtuin/treejson
Author: Richard Tuin
Author-email: richard@newnative.nl
License: MIT
Platform: UNKNOWN
